[{"id":"c50d983b19a82143","type":"inject","z":"b80a87890215bee5","name":"False","props":[{"p":"payload.xBool","v":"false","vt":"bool"}],"repeat":"2","crontab":"","once":true,"onceDelay":"0","topic":"","x":210,"y":100,"wires":[["a8aafc7fba78a3f7"]]},{"id":"a8aafc7fba78a3f7","type":"nvl-send","z":"b80a87890215bee5","name":"","definition":"VAR_GLOBAL\n    xBool:  BOOL;\nEND_VAR","listId":"20","globaltypes":"","x":460,"y":120,"wires":[["108561ce223cbdbd"]]},{"id":"b12484c2cb44f68a","type":"nvl-receive","z":"b80a87890215bee5","name":"","definition":"VAR_GLOBAL\n    xBool:  BOOL;\nEND_VAR","listId":"20","globaltypes":"","x":470,"y":460,"wires":[["a987fc9f23aee821"]]},{"id":"984a2a8b024ae340","type":"inject","z":"b80a87890215bee5","name":"True","props":[{"p":"payload.xBool","v":"true","vt":"bool"}],"repeat":"2","crontab":"","once":true,"onceDelay":"1","topic":"","x":210,"y":140,"wires":[["a8aafc7fba78a3f7"]]},{"id":"108561ce223cbdbd","type":"udp out","z":"b80a87890215bee5","name":"","addr":"127.0.0.1","iface":"","port":"1202","ipv":"udp4","outport":"","base64":false,"multicast":"false","x":690,"y":220,"wires":[]},{"id":"c02d0fcb37cd2534","type":"udp in","z":"b80a87890215bee5","name":"","iface":"","port":"1202","ipv":"udp4","multicast":"false","group":"","datatype":"buffer","x":220,"y":520,"wires":[["b12484c2cb44f68a","3aba0f4fbc824cb4"]]},{"id":"a987fc9f23aee821","type":"debug","z":"b80a87890215bee5","name":"","active":true,"tosidebar":false,"console":false,"tostatus":true,"complete":"payload.xBool","targetType":"msg","statusVal":"payload.xBool","statusType":"auto","x":690,"y":460,"wires":[]},{"id":"37188e44eb15465e","type":"nvl-send","z":"b80a87890215bee5","name":"","definition":"VAR_GLOBAL\n    sString:    STRING;\n    lrNumber:   LREAL;\n    iInt:       INT;\nEND_VAR","listId":"10","globaltypes":"b2c7564cfe776a2d","x":460,"y":320,"wires":[["108561ce223cbdbd"]]},{"id":"2d8a37f7e010ba60","type":"inject","z":"b80a87890215bee5","name":"Init","props":[{"p":"payload"}],"repeat":"","crontab":"","once":true,"onceDelay":"0","topic":"","payload":"{\"sString\":\"Init\",\"lrNumber\":0.123,\"iInt\":456}","payloadType":"json","x":210,"y":240,"wires":[["37188e44eb15465e"]]},{"id":"13debae28a468c2a","type":"inject","z":"b80a87890215bee5","name":"lrNumber","props":[{"p":"payload.lrNumber","v":"","vt":"date"}],"repeat":"2","crontab":"","once":true,"onceDelay":"0.5","topic":"","x":230,"y":280,"wires":[["37188e44eb15465e"]]},{"id":"3aba0f4fbc824cb4","type":"nvl-receive","z":"b80a87890215bee5","name":"","definition":"VAR_GLOBAL\n    sString:    STRING;\n    lrNumber:   LREAL;\n    iInt:       INT;\nEND_VAR","listId":"10","globaltypes":"","x":470,"y":580,"wires":[["a8596d4bc1fce544","051e9a686566065f","c4d40a2ed319df82"]]},{"id":"a8596d4bc1fce544","type":"debug","z":"b80a87890215bee5","name":"","active":true,"tosidebar":false,"console":false,"tostatus":true,"complete":"payload.sString","targetType":"msg","statusVal":"payload.sString","statusType":"auto","x":700,"y":580,"wires":[]},{"id":"051e9a686566065f","type":"debug","z":"b80a87890215bee5","name":"","active":true,"tosidebar":false,"console":false,"tostatus":true,"complete":"payload.lrNumber","targetType":"msg","statusVal":"payload.sString","statusType":"auto","x":700,"y":640,"wires":[]},{"id":"c4d40a2ed319df82","type":"debug","z":"b80a87890215bee5","name":"","active":true,"tosidebar":false,"console":false,"tostatus":true,"complete":"payload.iInt","targetType":"msg","statusVal":"payload.sString","statusType":"auto","x":680,"y":700,"wires":[]},{"id":"f6888eac2753fe42","type":"inject","z":"b80a87890215bee5","name":"sString","props":[{"p":"payload.sString","v":"New sentence.","vt":"str"},{"p":"topic","vt":"str"}],"repeat":"","crontab":"","once":false,"onceDelay":0.1,"topic":"","x":210,"y":320,"wires":[["37188e44eb15465e"]]},{"id":"dac469aa46574e75","type":"inject","z":"b80a87890215bee5","name":"iInt = 5","props":[{"p":"payload.iInt","v":"5","vt":"num"}],"repeat":"","crontab":"","once":false,"onceDelay":0.1,"topic":"","x":210,"y":360,"wires":[["37188e44eb15465e"]]},{"id":"6d2b72feaffc791d","type":"inject","z":"b80a87890215bee5","name":"iInt = 4","props":[{"p":"payload.iInt","v":"4","vt":"num"}],"repeat":"","crontab":"","once":false,"onceDelay":0.1,"topic":"","x":210,"y":400,"wires":[["37188e44eb15465e"]]},{"id":"b2c7564cfe776a2d","type":"nvl-datatypes","name":"Test","datatypes":"TYPE E_Enum :\n    (\n    member0 := 0,\n    member1,\n    memberx := 5,\n    member100 := 100\n    );\nEND_TYPE\n\n//Structure definition\nTYPE ST_MyStruct:\nSTRUCT\n    xBool:      BOOL;\n    bByte:      BYTE;\nEND_STRUCT\nEND_TYPE\n\n//Enumeration definition\nTYPE ENUM_Light: (\n    Red,\n    Orange,\n    Green := 10\n);\nEND_TYPE"}]